<xml xmlns:o="urn:schemas-microsoft-com:office:office">
 <o:MainFile HRef="../index.html"/>
 <o:File HRef="image299.png"/>
 <o:File HRef="image300.png"/>
 <o:File HRef="image301.png"/>
 <o:File HRef="image309.wmz"/>
 <o:File HRef="image308.png"/>
 <o:File HRef="image312.png"/>
 <o:File HRef="image322.png"/>
 <o:File HRef="image323.png"/>
 <o:File HRef="image331.png"/>
 <o:File HRef="Page342.html"/>
 <o:File HRef="image360.wmz"/>
 <o:File HRef="image359.png"/>
 <o:File HRef="image363.png"/>
 <o:File HRef="image365.wmz"/>
 <o:File HRef="image364.png"/>
 <o:File HRef="image369.png"/>
 <o:File HRef="image370.png"/>
 <o:File HRef="Page372.html"/>
 <o:File HRef="image389.png"/>
 <o:File HRef="image390.png"/>
 <o:File HRef="image395.png"/>
 <o:File HRef="image396.png"/>
 <o:File HRef="image398.wmz"/>
 <o:File HRef="image397.png"/>
 <o:File HRef="Page402.html"/>
 <o:File HRef="image411.png"/>
 <o:File HRef="image415.png"/>
 <o:File HRef="image427.wmz"/>
 <o:File HRef="image424.png"/>
 <o:File HRef="filelist.xml"/>
</xml>